LICENSE
README.md
setup.cfg
setup.py
./canvasdl/__init__.py
./canvasdl/asset_types/__init__.py
./canvasdl/asset_types/assignment.py
./canvasdl/asset_types/base.py
./canvasdl/asset_types/canvas.py
./canvasdl/asset_types/course.py
./canvasdl/asset_types/edstem.py
./canvasdl/asset_types/gradescope.py
./canvasdl/asset_types/piazza.py
./canvasdl/asset_types/section.py
./canvasdl/asset_types/streams.py
./canvasdl/asset_types/video.py
./canvasdl/assets/templates/announ.css
./canvasdl/checkers/__init__.py
./canvasdl/checkers/announ.py
./canvasdl/checkers/base.py
./canvasdl/checkers/drive.py
./canvasdl/checkers/edstem.py
./canvasdl/checkers/gradescope.py
./canvasdl/checkers/piazza.py
./canvasdl/checkers/website.py
./canvasdl/checkers/canvas/__init__.py
./canvasdl/checkers/canvas/announ.py
./canvasdl/checkers/canvas/assignment.py
./canvasdl/checkers/canvas/base.py
./canvasdl/checkers/canvas/files.py
./canvasdl/checkers/canvas/tab.py
./canvasdl/checkers/canvas/videos.py
./canvasdl/core/__init__.py
./canvasdl/core/checkservice.py
./canvasdl/core/client.py
./canvasdl/core/courseinfo.py
./canvasdl/core/coursemaker.py
./canvasdl/core/main.py
./canvasdl/core/starter.py
./canvasdl/ui/__init__.py
./canvasdl/ui/downloadprogress.py
./canvasdl/ui/popup.py
./canvasdl/ui/progressbar.py
./canvasdl/ui/progressmanager.py
./canvasdl/ui/silentpopup.py
./canvasdl/ui/userinterface.py
./canvasdl/ui/widget.py
./canvasdl/ui/widgetui.py
./canvasdl/utils/__init__.py
./canvasdl/utils/announcements.py
./canvasdl/utils/argparser.py
./canvasdl/utils/calendar.py
./canvasdl/utils/config.py
./canvasdl/utils/configchecker.py
./canvasdl/utils/configmaker.py
./canvasdl/utils/path.py
./canvasdl/utils/shortcutmaker.py
./canvasdl/utils/threading.py
./canvasdl/utils/time.py
canvasdl.egg-info/PKG-INFO
canvasdl.egg-info/SOURCES.txt
canvasdl.egg-info/dependency_links.txt
canvasdl.egg-info/entry_points.txt
canvasdl.egg-info/requires.txt
canvasdl.egg-info/top_level.txt