Metadata-Version: 2.1
Name: canvasdl
Version: 1.4.18
Summary: course content synchronizer
Home-page: https://github.com/quintenroets/canvasdl
Download-URL: https://github.com/quintenroets/canvasdl/archive/refs/tags/v1.4.11.tar.gz
Author: Quinten Roets
Author-email: quinten.roets@gmail.com
License: MIT
License-File: LICENSE
